[
    {
        "id": "1",
        "title": "how",
        "description": "hello",
        "src": "https://image.tmdb.org/t/p/w500/bQXAqRx2Fgc46uCVWgoPz5L5Dtr.jpg"
    },
    {
        "id": "2",
        "title": "how",
        "description": "hello",
        "src": "https://image.tmdb.org/t/p/w500/60UN7vvcWWggLe0Uz9EFZJx718P.jpg"
    },
    {
        "id": "3",
        "title": "how",
        "description": "hello",
        "src": "https://image.tmdb.org/t/p/w500/u6WzMRpTkGzIlfsPNtDfIBfEy9z.jpg"
    },
    {
        "id": "4",
        "title": "how",
        "description": "hello",
        "src": "https://image.tmdb.org/t/p/w500/3G8xATwPSnkvkxFGquKnG2xobp7.jpg"
    },
    {
        "id": "5",
        "title": "how",
        "description": "hello",
        "src": "https://image.tmdb.org/t/p/w500/fBNnj5bQ5YhzPUzxIW1UvLVZepP.jpg"
    }
]